wemail.py
wemail-2020.8.14.dist-info/METADATA
wemail-2020.8.14.dist-info/WHEEL
wemail-2020.8.14.dist-info/entry_points.txt
wemail-2020.8.14.dist-info/top_level.txt
wemail-2020.8.14.dist-info/RECORD
