Metadata-Version: 2.1
Name: wemail
Version: 2020.8.14
Summary: UNKNOWN
Home-page: https://github.com/waynew/wemail
Author: Wayne Werner
Author-email: wayne@waynewerner.com
License: UNKNOWN
Platform: UNKNOWN
Provides-Extra: build
Requires-Dist: wheel ; extra == 'build'
Provides-Extra: html
Requires-Dist: mistletoe ; extra == 'html'
Provides-Extra: test
Requires-Dist: pytest ; extra == 'test'
Requires-Dist: pytest-cov ; extra == 'test'
Requires-Dist: aiosmtpd ; extra == 'test'
Requires-Dist: mistletoe ; extra == 'test'
